pystodon/__init__.py
pystodon/__main__.py
pystodon/commands.py
pystodon/lib/__init__.py
pystodon/lib/command.py
pystodon/lib/utils.py
pystodon/utils/__init__.py
pystodon/utils/cli_args.py
pystodon/utils/logging.py
pystodon-0.1.0.dist-info/entry_points.txt
pystodon-0.1.0.dist-info/LICENSE
pystodon-0.1.0.dist-info/METADATA
pystodon-0.1.0.dist-info/WHEEL
pystodon-0.1.0.dist-info/RECORD
