Metadata-Version: 2.1
Name: pystodon
Version: 0.1.0
Summary: 
Author: slashtechno
Author-email: 77907286+slashtechno@users.noreply.github.com
Requires-Python: >=3.11,<4.0
Classifier: License :: OSI Approved :: MIT License
Classifier: Programming Language :: Python
Classifier: Programming Language :: Python :: 3
Classifier: Programming Language :: Python :: 3.11
Classifier: Programming Language :: Python :: 3.12
Requires-Dist: airportsdata (>=20230717,<20230718)
Requires-Dist: beautifulsoup4 (>=4.12.2,<5.0.0)
Requires-Dist: dateparser (>=1.2.0,<2.0.0)
Requires-Dist: httpx (>=0.24.1,<0.25.0)
Requires-Dist: loguru (>=0.7.0,<0.8.0)
Requires-Dist: mastodon-py (>=1.8.1,<2.0.0)
Requires-Dist: peewee (>=3.17.5,<4.0.0)
Requires-Dist: psycopg2-binary (>=2.9.9,<3.0.0)
Requires-Dist: python-dotenv (>=1.0.0,<2.0.0)
Requires-Dist: pytz (>=2023.3,<2024.0)
Requires-Dist: trio (>=0.22.2,<0.23.0)
